{"allContent":{"docusaurus-plugin-content-docs":{"default":{"loadedVersions":[{"versionName":"current","label":"Next","banner":null,"badge":false,"noIndex":false,"className":"docs-version-current","path":"/hl-docs/docs","tagsPath":"/hl-docs/docs/tags","isLast":true,"routePriority":-1,"sidebarFilePath":"/home/felipecsl/prj/hl.lima.gl/sidebars.ts","contentPath":"/home/felipecsl/prj/hl.lima.gl/docs","docs":[{"id":"accessories","title":"Accessories","description":"Helpers to add services like Postgres/Redis using Compose fragments.","source":"@site/docs/accessories.md","sourceDirName":".","slug":"/accessories","permalink":"/hl-docs/docs/accessories","draft":false,"unlisted":false,"tags":[],"version":"current","frontMatter":{},"sidebar":"docs","previous":{"title":"Health Checks","permalink":"/hl-docs/docs/health-checks"},"next":{"title":"Typical Workflow","permalink":"/hl-docs/docs/workflow"}},{"id":"commands/accessory-postgres","title":"hl accessory add postgres","description":"Adds a healthy Postgres service via compose.postgres.yml and wires DATABASE_URL.","source":"@site/docs/commands/accessory-postgres.md","sourceDirName":"commands","slug":"/commands/accessory-postgres","permalink":"/hl-docs/docs/commands/accessory-postgres","draft":false,"unlisted":false,"tags":[],"version":"current","frontMatter":{},"sidebar":"docs","previous":{"title":"hl env","permalink":"/hl-docs/docs/commands/env"},"next":{"title":"hl accessory add redis","permalink":"/hl-docs/docs/commands/accessory-redis"}},{"id":"commands/accessory-redis","title":"hl accessory add redis","description":"Adds a Redis service via compose.redis.yml and wires REDIS_URL.","source":"@site/docs/commands/accessory-redis.md","sourceDirName":"commands","slug":"/commands/accessory-redis","permalink":"/hl-docs/docs/commands/accessory-redis","draft":false,"unlisted":false,"tags":[],"version":"current","frontMatter":{},"sidebar":"docs","previous":{"title":"hl accessory add postgres","permalink":"/hl-docs/docs/commands/accessory-postgres"},"next":{"title":"FAQ","permalink":"/hl-docs/docs/faq"}},{"id":"commands/deploy","title":"hl deploy","description":"Export commit → build & push → migrations → retag → restart (systemd) → health‑gate.","source":"@site/docs/commands/deploy.md","sourceDirName":"commands","slug":"/commands/deploy","permalink":"/hl-docs/docs/commands/deploy","draft":false,"unlisted":false,"tags":[],"version":"current","frontMatter":{},"sidebar":"docs","previous":{"title":"hl init","permalink":"/hl-docs/docs/commands/init"},"next":{"title":"hl rollback","permalink":"/hl-docs/docs/commands/rollback"}},{"id":"commands/env","title":"hl env","description":"Some setups distinguish build‑time vs runtime env. If enabled in your build, you may see:","source":"@site/docs/commands/env.md","sourceDirName":"commands","slug":"/commands/env","permalink":"/hl-docs/docs/commands/env","draft":false,"unlisted":false,"tags":[],"version":"current","frontMatter":{},"sidebar":"docs","previous":{"title":"hl secrets","permalink":"/hl-docs/docs/commands/secrets"},"next":{"title":"hl accessory add postgres","permalink":"/hl-docs/docs/commands/accessory-postgres"}},{"id":"commands/init","title":"hl init","description":"Create per‑app runtime home, Compose file(s), hl.yml, and a systemd unit.","source":"@site/docs/commands/init.md","sourceDirName":"commands","slug":"/commands/init","permalink":"/hl-docs/docs/commands/init","draft":false,"unlisted":false,"tags":[],"version":"current","frontMatter":{},"sidebar":"docs","previous":{"title":"Command Overview","permalink":"/hl-docs/docs/commands/overview"},"next":{"title":"hl deploy","permalink":"/hl-docs/docs/commands/deploy"}},{"id":"commands/overview","title":"Command Overview","description":"Names/flags may differ depending on implementation maturity, but this is the intended surface.","source":"@site/docs/commands/overview.md","sourceDirName":"commands","slug":"/commands/overview","permalink":"/hl-docs/docs/commands/overview","draft":false,"unlisted":false,"tags":[],"version":"current","frontMatter":{},"sidebar":"docs","previous":{"title":"Typical Workflow","permalink":"/hl-docs/docs/workflow"},"next":{"title":"hl init","permalink":"/hl-docs/docs/commands/init"}},{"id":"commands/rollback","title":"hl rollback","description":"Fast rollback by retagging :latest to a known good SHA, then restarting with health‑gate.","source":"@site/docs/commands/rollback.md","sourceDirName":"commands","slug":"/commands/rollback","permalink":"/hl-docs/docs/commands/rollback","draft":false,"unlisted":false,"tags":[],"version":"current","frontMatter":{},"sidebar":"docs","previous":{"title":"hl deploy","permalink":"/hl-docs/docs/commands/deploy"},"next":{"title":"hl secrets","permalink":"/hl-docs/docs/commands/secrets"}},{"id":"commands/secrets","title":"hl secrets","description":"Manage runtime secrets stored in the app’s .env on the server (mode 0600). Do not bake secrets into images.","source":"@site/docs/commands/secrets.md","sourceDirName":"commands","slug":"/commands/secrets","permalink":"/hl-docs/docs/commands/secrets","draft":false,"unlisted":false,"tags":[],"version":"current","frontMatter":{},"sidebar":"docs","previous":{"title":"hl rollback","permalink":"/hl-docs/docs/commands/rollback"},"next":{"title":"hl env","permalink":"/hl-docs/docs/commands/env"}},{"id":"configuration","title":"Configuration (hl.yml)","description":"Server‑owned file at /home//hl/apps//hl.yml.","source":"@site/docs/configuration.md","sourceDirName":".","slug":"/configuration","permalink":"/hl-docs/docs/configuration","draft":false,"unlisted":false,"tags":[],"version":"current","frontMatter":{},"sidebar":"docs","previous":{"title":"How It Works","permalink":"/hl-docs/docs/how-it-works"},"next":{"title":"Health Checks","permalink":"/hl-docs/docs/health-checks"}},{"id":"faq","title":"FAQ","description":"Where does the build context come from?","source":"@site/docs/faq.md","sourceDirName":".","slug":"/faq","permalink":"/hl-docs/docs/faq","draft":false,"unlisted":false,"tags":[],"version":"current","frontMatter":{},"sidebar":"docs","previous":{"title":"hl accessory add redis","permalink":"/hl-docs/docs/commands/accessory-redis"}},{"id":"getting-started","title":"Getting Started","description":"This guide shows a single‑host setup where a Git push to a bare repo on the server triggers a build and restart.","source":"@site/docs/getting-started.md","sourceDirName":".","slug":"/getting-started","permalink":"/hl-docs/docs/getting-started","draft":false,"unlisted":false,"tags":[],"version":"current","frontMatter":{},"sidebar":"docs","previous":{"title":"hl","permalink":"/hl-docs/docs/intro"},"next":{"title":"How It Works","permalink":"/hl-docs/docs/how-it-works"}},{"id":"health-checks","title":"Health Checks","description":"hl runs a short‑lived container on the app network to hit http.","source":"@site/docs/health-checks.md","sourceDirName":".","slug":"/health-checks","permalink":"/hl-docs/docs/health-checks","draft":false,"unlisted":false,"tags":[],"version":"current","frontMatter":{},"sidebar":"docs","previous":{"title":"Configuration (hl.yml)","permalink":"/hl-docs/docs/configuration"},"next":{"title":"Accessories","permalink":"/hl-docs/docs/accessories"}},{"id":"how-it-works","title":"How It Works","description":"1. You Push to a bare repo on the server.","source":"@site/docs/how-it-works.md","sourceDirName":".","slug":"/how-it-works","permalink":"/hl-docs/docs/how-it-works","draft":false,"unlisted":false,"tags":[],"version":"current","frontMatter":{},"sidebar":"docs","previous":{"title":"Getting Started","permalink":"/hl-docs/docs/getting-started"},"next":{"title":"Configuration (hl.yml)","permalink":"/hl-docs/docs/configuration"}},{"id":"intro","title":"hl","description":"hl is a tiny, deterministic “git‑push deploys” CLI for single‑host deployments. Its goal is to keep deployments dead‑simple, explicit, and reliable — without adopting a full orchestrator.","source":"@site/docs/intro.md","sourceDirName":".","slug":"/intro","permalink":"/hl-docs/docs/intro","draft":false,"unlisted":false,"tags":[],"version":"current","sidebarPosition":1,"frontMatter":{"sidebar_position":1},"sidebar":"docs","next":{"title":"Getting Started","permalink":"/hl-docs/docs/getting-started"}},{"id":"workflow","title":"Typical Workflow","description":"1) Bootstrap: hl init ...","source":"@site/docs/workflow.md","sourceDirName":".","slug":"/workflow","permalink":"/hl-docs/docs/workflow","draft":false,"unlisted":false,"tags":[],"version":"current","frontMatter":{},"sidebar":"docs","previous":{"title":"Accessories","permalink":"/hl-docs/docs/accessories"},"next":{"title":"Command Overview","permalink":"/hl-docs/docs/commands/overview"}}],"drafts":[],"sidebars":{"docs":[{"type":"doc","id":"intro"},{"type":"doc","id":"getting-started"},{"type":"doc","id":"how-it-works"},{"type":"doc","id":"configuration"},{"type":"doc","id":"health-checks"},{"type":"doc","id":"accessories"},{"type":"doc","id":"workflow"},{"type":"category","label":"Commands","collapsed":false,"items":[{"type":"doc","id":"commands/overview"},{"type":"doc","id":"commands/init"},{"type":"doc","id":"commands/deploy"},{"type":"doc","id":"commands/rollback"},{"type":"doc","id":"commands/secrets"},{"type":"doc","id":"commands/env"},{"type":"doc","id":"commands/accessory-postgres"},{"type":"doc","id":"commands/accessory-redis"}],"collapsible":true},{"type":"doc","id":"faq"}]}}]}},"docusaurus-plugin-content-pages":{"default":[{"type":"jsx","permalink":"/hl-docs/","source":"@site/src/pages/index.jsx"}]},"docusaurus-plugin-debug":{},"docusaurus-plugin-svgr":{},"docusaurus-theme-classic":{},"docusaurus-bootstrap-plugin":{},"docusaurus-mdx-fallback-plugin":{}}}